output_layer/libreline/classifier_top/src/reg_intN_clr_load.v

module reg_intN_clr_load #(
    parameter N = 3
)(
    input  wire           clk,
    input  wire           rst_n,
    input  wire           clr,
    input  wire           load,
    input  wire [N-1:0]   d,
    output reg  [N-1:0]   q
);
    always @(posedge clk or negedge rst_n) begin
        if (!rst_n) q <= '0;
        else if (clr) q <= '0;
        else if (load) q <= d;
    end
endmodule

output_layer/libreline/classifier_top/src/reg_int20_clr_load.v
// ============================================================
// 3) Registro signed: int8 con clear y load
//    - clr: fuerza 0
//    - load: carga d
//    Prioridad: clr > load > hold
// ============================================================


module reg_int20_clr_load (
    input  wire               clk,
    input  wire               rst_n,   // reset async activo en 0
    input  wire               clr,     // limpia a 0 (sync)
    input  wire               load,    // carga d (sync)
    input  wire signed [19:0] d,
    output reg  signed [19:0] q
);
    always @(posedge clk or negedge rst_n) begin
        if (!rst_n)
            q <= '0;
        else if (clr)
            q <= '0;
        else if (load)
            q <= d;
    end
endmodule

output_layer/rtl/cmp_gt_int20.v

module cmp_gt_int20 (
    input  wire signed [19:0] a,
    input  wire signed [19:0] b,
    output wire               gt
);
    assign gt = (a > b);
endmodule

output_layer/rtl/add_int12_int20_to_int20.v
// ============================================================
// 2) Sumador signed: int12 + int20 -> int20
// ============================================================


module add_int12_int20_to_int20 (
    input  wire signed [11:0] in12, // int12
    input  wire signed [19:0] in20,  // int20
    output wire signed [19:0] out20  // int20
);
    wire signed [19:0] in12_ext;

    // Extensión de signo de 12 a 20 bits
    assign in12_ext = {{8{in12[11]}}, in12};

    // Suma; se mantiene en 20 bits (overflow se trunca naturalmente)
    assign out20 = in20 + in12_ext;
endmodule

output_layer/rtl/mul_int4_int8_to_int12.v
// ============================================================
// 1) Multiplicador signed: int4 * int8 -> int12
// ============================================================

module mul_int4_int8_to_int12 (
    input  wire signed [3:0]  a,   // int4
    input  wire signed [7:0]  b,   // int8
    output wire signed [11:0] y    // int12
);
    // 4+8 = 12 bits exactos para el producto en 2's complement
    assign y = a * b;
endmodule

output_layer/libreline/classifier_top/src/classifier_mac_argmax_modular.v
`timescale 1ns/1ps

module classifier_mac_argmax_modular #(
    parameter int CLASS_BITS = 3
)(
    input  wire               clk,
    input  wire               rst_n,

    // Datos por ciclo (válidos cuando new_feat=1)
    input  wire signed [3:0]  x_int4,
    input  wire signed [7:0]  w_int8,

    // Eventos
    input  wire               new_feat,   // acumula 1 vez
    input  wire               new_class,  // terminó clase: compara/actualiza max y limpia acumulador

    // ID de clase (válido cuando new_class=1)
    input  wire [CLASS_BITS-1:0] class_id,

    // Salidas útiles
    output wire signed [19:0] acc20,
    output wire signed [19:0] max_score,
    output wire [CLASS_BITS-1:0] max_class
);

    // -------------------------
    // Wires internos
    // -------------------------
    wire signed [11:0] prod12;
    wire signed [19:0] acc_fb;
    wire signed [19:0] sum20;

    wire signed [19:0] max_score_q;
    wire               gt;
    wire               update_max;

    // -------------------------
    // 1) Multiplicador: int4 * int8 -> int12
    // -------------------------
    mul_int4_int8_to_int12 u_mul (
        .a (x_int4),
        .b (w_int8),
        .y (prod12)
    );

    // -------------------------
    // 2) Sumador: int12 + int20 -> int20
    //    (in12 = prod12, in20 = acc_fb)
    // -------------------------
    add_int12_int20_to_int20 u_add (
        .in12 (prod12),
        .in20 (acc_fb),
        .out20(sum20)
    );

    // -------------------------
    // 3) Acumulador (reg_int20_clr_load)
    //    - load cuando new_feat=1
    //    - clear cuando new_class=1 (sync)
    // -------------------------
    reg_int20_clr_load u_acc (
        .clk  (clk),
        .rst_n(rst_n),
        .clr  (new_class),  // clear sync activo HIGH
        .load (new_feat & ~new_class),
        .d    (sum20),
        .q    (acc_fb)
    );

    assign acc20 = acc_fb;

    // -------------------------
    // 4) Comparador: acc_fb > max_score_q
    // -------------------------
    cmp_gt_int20 u_cmp (
        .a  (acc_fb),
        .b  (max_score_q),
        .gt (gt)
    );

    // Solo actualizamos max al final de cada clase
    assign update_max = new_class & gt;

    // -------------------------
    // 5) Registro max_score (usa el mismo reg_int20_clr_load)
    //    - clr SOLO por reset (clr amarrado a 0)
    //    - load solo cuando update_max=1
    // -------------------------
    reg_int20_clr_load u_max_score (
        .clk  (clk),
        .rst_n(rst_n),
        .clr  (1'b0),        // SOLO reset borra el max_score
        .load (update_max),
        .d    (acc_fb),
        .q    (max_score_q)
    );

    assign max_score = max_score_q;

    // -------------------------
    // 6) Registro max_class (reg genérico N bits)
    //    - clr SOLO por reset (clr amarrado a 0)
    //    - load cuando update_max=1
    // -------------------------
    reg_intN_clr_load #(
        .N(CLASS_BITS)
    ) u_max_class (
        .clk  (clk),
        .rst_n(rst_n),
        .clr  (1'b0),         // SOLO reset borra el max_class
        .load (update_max),
        .d    (class_id),
        .q    (max_class)
    );

endmodule

output_layer/tb/tb_classifier_mac_argmax_1.v
`timescale 1ns/1ps

module tb_classifier_mac_argmax_1;

  // ----------------------------
  // Parámetros del DUT
  // ----------------------------
  localparam int CLASS_BITS = 3;

  // ----------------------------
  // Señales DUT
  // ----------------------------
  reg  clk;
  reg  rst_n;

  reg  signed [3:0]  x_int4;
  reg  signed [7:0]  w_int8;
  reg                new_feat;
  reg                new_class;
  reg  [CLASS_BITS-1:0] class_id;

  wire signed [19:0] acc20;
  wire signed [19:0] max_score;
  wire [CLASS_BITS-1:0] max_class;

  // ----------------------------
  // Instancia DUT
  // ----------------------------
  classifier_mac_argmax_modular #(
    .CLASS_BITS(CLASS_BITS)
  ) dut (
    .clk      (clk),
    .rst_n    (rst_n),
    .x_int4   (x_int4),
    .w_int8   (w_int8),
    .new_feat (new_feat),
    .new_class(new_class),
    .class_id (class_id),
    .acc20    (acc20),
    .max_score(max_score),
    .max_class(max_class)
  );

  // ----------------------------
  // Clock 100MHz (10ns)
  // ----------------------------
  initial clk = 1'b0;
  always #5 clk = ~clk;

  // ----------------------------
  // Task: aplicar un "ciclo" del stream
  //   - setea señales
  //   - espera flanco positivo
  // ----------------------------
  task drive_cycle(
    input reg feat,
    input reg cls,
    input signed [3:0] x,
    input signed [7:0] w,
    input [CLASS_BITS-1:0] cid
  );
  begin
    new_feat  = feat;
    new_class = cls;
    x_int4    = x;
    w_int8    = w;
    class_id  = cid;

    @(posedge clk);
    #1; // pequeño delay para leer señales estables post-flanco
  end
  endtask

  // ----------------------------
  // Test
  // ----------------------------
  integer expected;

  initial begin
    // VCD para GTKWave
    $dumpfile("tb_classifier.vcd");
    $dumpvars(0, tb_classifier_mac_argmax_1);

    // init
    x_int4    = '0;
    w_int8    = '0;
    new_feat  = 1'b0;
    new_class = 1'b0;
    class_id  = '0;

    expected = 0;

    // reset
    rst_n = 1'b0;
    repeat (2) @(posedge clk);
    rst_n = 1'b1;
    @(posedge clk);

    // ------------------------------------------------------------
    // Stream (15 ciclos) EXACTO como el que imprimiste
    // ------------------------------------------------------------

    // Clase 0 (4 feats)
    drive_cycle(1, 0,  4'sd5,   8'sd36,  3'd0);
    drive_cycle(1, 0,  4'sd3,   8'sd69,  3'd0);
    drive_cycle(1, 0,  4'sd1,  -8'sd127, 3'd0);
    drive_cycle(1, 0,  4'sd0,  -8'sd39,  3'd0);
    // end class 0
    drive_cycle(0, 1,  4'sd0,   8'sd0,   3'd0);

    // Clase 1
    drive_cycle(1, 0,  4'sd5,   8'sd21,  3'd1);
    drive_cycle(1, 0,  4'sd3,  -8'sd13,  3'd1);
    drive_cycle(1, 0,  4'sd1,  -8'sd5,   3'd1);
    drive_cycle(1, 0,  4'sd0,  -8'sd46,  3'd1);
    // end class 1
    drive_cycle(0, 1,  4'sd0,   8'sd0,   3'd1);

    // Clase 2
    drive_cycle(1, 0,  4'sd5,  -8'sd68,  3'd2);
    drive_cycle(1, 0,  4'sd3,  -8'sd48,  3'd2);
    drive_cycle(1, 0,  4'sd1,   8'sd88,  3'd2);
    drive_cycle(1, 0,  4'sd0,   8'sd81,  3'd2);
    // end class 2 (última)
    drive_cycle(0, 1,  4'sd0,   8'sd0,   3'd2);

    // baja flags
    new_feat  = 1'b0;
    new_class = 1'b0;

    // Espera un poco para observar
    @(posedge clk);
    #1;

    // Check final
    $display("FINAL: max_class=%0d, max_score=%0d", max_class, max_score);

    if (max_class !== expected[CLASS_BITS-1:0]) begin
      $display("FAIL: expected max_class=%0d, got %0d", expected, max_class);
      $fatal;
    end else begin
      $display("PASS: expected max_class=%0d matches got %0d", expected, max_class);
    end

    $finish;
  end

endmodule

output_layer/sim/wave/tb_classifier.vcd
$date
	Sun Feb  8 04:08:41 2026
$end
$version
	Icarus Verilog
$end
$timescale
	1ps
$end
$scope module tb_classifier_mac_argmax_1 $end
$var wire 20 ! max_score [19:0] $end
$var wire 3 " max_class [2:0] $end
$var wire 20 # acc20 [19:0] $end
$var parameter 32 $ CLASS_BITS $end
$var reg 3 % class_id [2:0] $end
$var reg 1 & clk $end
$var reg 1 ' new_class $end
$var reg 1 ( new_feat $end
$var reg 1 ) rst_n $end
$var reg 8 * w_int8 [7:0] $end
$var reg 4 + x_int4 [3:0] $end
$var integer 32 , expected [31:0] $end
$scope module dut $end
$var wire 20 - acc20 [19:0] $end
$var wire 3 . class_id [2:0] $end
$var wire 1 & clk $end
$var wire 20 / max_score [19:0] $end
$var wire 1 ' new_class $end
$var wire 1 ( new_feat $end
$var wire 1 ) rst_n $end
$var wire 1 0 update_max $end
$var wire 8 1 w_int8 [7:0] $end
$var wire 4 2 x_int4 [3:0] $end
$var wire 20 3 sum20 [19:0] $end
$var wire 12 4 prod12 [11:0] $end
$var wire 20 5 max_score_q [19:0] $end
$var wire 3 6 max_class [2:0] $end
$var wire 1 7 gt $end
$var wire 20 8 acc_fb [19:0] $end
$var parameter 32 9 CLASS_BITS $end
$scope module u_acc $end
$var wire 1 & clk $end
$var wire 1 ' clr $end
$var wire 1 : load $end
$var wire 1 ) rst_n $end
$var wire 20 ; d [19:0] $end
$var reg 20 < q [19:0] $end
$upscope $end
$scope module u_add $end
$var wire 20 = in20 [19:0] $end
$var wire 20 > out20 [19:0] $end
$var wire 20 ? in12_ext [19:0] $end
$var wire 12 @ in12 [11:0] $end
$upscope $end
$scope module u_cmp $end
$var wire 20 A a [19:0] $end
$var wire 1 7 gt $end
$var wire 20 B b [19:0] $end
$upscope $end
$scope module u_max_class $end
$var wire 1 & clk $end
$var wire 1 C clr $end
$var wire 3 D d [2:0] $end
$var wire 1 0 load $end
$var wire 1 ) rst_n $end
$var parameter 32 E N $end
$var reg 3 F q [2:0] $end
$upscope $end
$scope module u_max_score $end
$var wire 1 & clk $end
$var wire 1 G clr $end
$var wire 20 H d [19:0] $end
$var wire 1 0 load $end
$var wire 1 ) rst_n $end
$var reg 20 I q [19:0] $end
$upscope $end
$scope module u_mul $end
$var wire 4 J a [3:0] $end
$var wire 8 K b [7:0] $end
$var wire 12 L y [11:0] $end
$upscope $end
$upscope $end
$scope task drive_cycle $end
$var reg 3 M cid [2:0] $end
$var reg 1 N cls $end
$var reg 1 O feat $end
$var reg 8 P w [7:0] $end
$var reg 4 Q x [3:0] $end
$upscope $end
$upscope $end
$enddefinitions $end
$comment Show the parameter values. $end
$dumpall
b11 E
b11 9
b11 $
$end
#0
$dumpvars
bx Q
bx P
xO
xN
bx M
b0 L
b0 K
b0 J
b0 I
b0 H
0G
b0 F
b0 D
0C
b0 B
b0 A
b0 @
b0 ?
b0 >
b0 =
b0 <
b0 ;
0:
b0 8
07
b0 6
b0 5
b0 4
b0 3
b0 2
b0 1
00
b0 /
b0 .
b0 -
b0 ,
b0 +
b0 *
0)
0(
0'
0&
b0 %
b0 #
b0 "
b0 !
$end
#5000
1&
#10000
0&
#15000
1)
1&
#20000
0&
#25000
b10110100 3
b10110100 ;
b10110100 >
b10110100 ?
1:
b10110100 4
b10110100 @
b10110100 L
b100100 *
b100100 1
b100100 K
b101 +
b101 2
b101 J
1(
b0 M
b100100 P
b101 Q
0N
1O
1&
#30000
0&
#35000
b101101000 3
b101101000 ;
b101101000 >
17
b10110100 #
b10110100 -
b10110100 8
b10110100 <
b10110100 =
b10110100 A
b10110100 H
1&
#36000
b110000011 3
b110000011 ;
b110000011 >
b11001111 ?
b1000101 *
b1000101 1
b1000101 K
b11001111 4
b11001111 @
b11001111 L
b11 +
b11 2
b11 J
b1000101 P
b11 Q
#40000
0&
#45000
b1001010010 3
b1001010010 ;
b1001010010 >
b110000011 #
b110000011 -
b110000011 8
b110000011 <
b110000011 =
b110000011 A
b110000011 H
1&
#46000
b100000100 3
b100000100 ;
b100000100 >
b11111111111110000001 ?
b10000001 *
b10000001 1
b10000001 K
b111110000001 4
b111110000001 @
b111110000001 L
b1 +
b1 2
b1 J
b10000001 P
b1 Q
#50000
0&
#55000
b10000101 3
b10000101 ;
b10000101 >
b100000100 #
b100000100 -
b100000100 8
b100000100 <
b100000100 =
b100000100 A
b100000100 H
1&
#56000
b100000100 3
b100000100 ;
b100000100 >
b0 ?
b11011001 *
b11011001 1
b11011001 K
b0 4
b0 @
b0 L
b0 +
b0 2
b0 J
b11011001 P
b0 Q
#60000
0&
#65000
1&
#66000
10
0:
b0 *
b0 1
b0 K
1'
0(
b0 P
1N
0O
#70000
0&
#75000
00
b0 3
b0 ;
b0 >
b0 #
b0 -
b0 8
b0 <
b0 =
b0 A
b0 H
07
b100000100 !
b100000100 /
b100000100 5
b100000100 B
b100000100 I
1&
#76000
1:
b1101001 3
b1101001 ;
b1101001 >
b1101001 ?
b1 %
b1 .
b1 D
b1101001 4
b1101001 @
b1101001 L
b10101 *
b10101 1
b10101 K
b101 +
b101 2
b101 J
0'
1(
b1 M
b10101 P
b101 Q
0N
1O
#80000
0&
#85000
b11010010 3
b11010010 ;
b11010010 >
b1101001 #
b1101001 -
b1101001 8
b1101001 <
b1101001 =
b1101001 A
b1101001 H
1&
#86000
b1000010 3
b1000010 ;
b1000010 >
b11111111111111011001 ?
b11110011 *
b11110011 1
b11110011 K
b111111011001 4
b111111011001 @
b111111011001 L
b11 +
b11 2
b11 J
b11110011 P
b11 Q
#90000
0&
#95000
b11011 3
b11011 ;
b11011 >
b1000010 #
b1000010 -
b1000010 8
b1000010 <
b1000010 =
b1000010 A
b1000010 H
1&
#96000
b111101 3
b111101 ;
b111101 >
b11111111111111111011 ?
b11111011 *
b11111011 1
b11111011 K
b111111111011 4
b111111111011 @
b111111111011 L
b1 +
b1 2
b1 J
b11111011 P
b1 Q
#100000
0&
#105000
b111000 3
b111000 ;
b111000 >
b111101 #
b111101 -
b111101 8
b111101 <
b111101 =
b111101 A
b111101 H
1&
#106000
b111101 3
b111101 ;
b111101 >
b0 ?
b11010010 *
b11010010 1
b11010010 K
b0 4
b0 @
b0 L
b0 +
b0 2
b0 J
b11010010 P
b0 Q
#110000
0&
#115000
1&
#116000
0:
b0 *
b0 1
b0 K
1'
0(
b0 P
1N
0O
#120000
0&
#125000
b0 3
b0 ;
b0 >
b0 #
b0 -
b0 8
b0 <
b0 =
b0 A
b0 H
1&
#126000
1:
b11111111111010101100 3
b11111111111010101100 ;
b11111111111010101100 >
b11111111111010101100 ?
b10 %
b10 .
b10 D
b111010101100 4
b111010101100 @
b111010101100 L
b10111100 *
b10111100 1
b10111100 K
b101 +
b101 2
b101 J
0'
1(
b10 M
b10111100 P
b101 Q
0N
1O
#130000
0&
#135000
b11111111110101011000 3
b11111111110101011000 ;
b11111111110101011000 >
b11111111111010101100 #
b11111111111010101100 -
b11111111111010101100 8
b11111111111010101100 <
b11111111111010101100 =
b11111111111010101100 A
b11111111111010101100 H
1&
#136000
b11111111111000011100 3
b11111111111000011100 ;
b11111111111000011100 >
b11111111111101110000 ?
b11010000 *
b11010000 1
b11010000 K
b111101110000 4
b111101110000 @
b111101110000 L
b11 +
b11 2
b11 J
b11010000 P
b11 Q
#140000
0&
#145000
b11111111110110001100 3
b11111111110110001100 ;
b11111111110110001100 >
b11111111111000011100 #
b11111111111000011100 -
b11111111111000011100 8
b11111111111000011100 <
b11111111111000011100 =
b11111111111000011100 A
b11111111111000011100 H
1&
#146000
b11111111111001110100 3
b11111111111001110100 ;
b11111111111001110100 >
b1011000 ?
b1011000 *
b1011000 1
b1011000 K
b1011000 4
b1011000 @
b1011000 L
b1 +
b1 2
b1 J
b1011000 P
b1 Q
#150000
0&
#155000
b11111111111011001100 3
b11111111111011001100 ;
b11111111111011001100 >
b11111111111001110100 #
b11111111111001110100 -
b11111111111001110100 8
b11111111111001110100 <
b11111111111001110100 =
b11111111111001110100 A
b11111111111001110100 H
1&
#156000
b11111111111001110100 3
b11111111111001110100 ;
b11111111111001110100 >
b0 ?
b1010001 *
b1010001 1
b1010001 K
b0 4
b0 @
b0 L
b0 +
b0 2
b0 J
b1010001 P
b0 Q
#160000
0&
#165000
1&
#166000
0:
b0 *
b0 1
b0 K
1'
0(
b0 P
1N
0O
#170000
0&
#175000
b0 3
b0 ;
b0 >
b0 #
b0 -
b0 8
b0 <
b0 =
b0 A
b0 H
1&
#176000
0'
